LICENSE
MANIFEST.in
setup.py
django_require2.egg-info/PKG-INFO
django_require2.egg-info/SOURCES.txt
django_require2.egg-info/dependency_links.txt
django_require2.egg-info/top_level.txt
require/__init__.py
require/conf.py
require/environments.py
require/helpers.py
require/models.py
require/storage.py
require/management/__init__.py
require/management/commands/__init__.py
require/management/commands/require_init.py
require/resources/almond.js
require/resources/app.build.js
require/resources/compiler.jar
require/resources/js.jar
require/resources/module.build.js
require/resources/r.js
require/resources/require.js
require/resources/tests/app.build.closure.js
require/resources/tests/app.build.js
require/resources/tests/main.js
require/resources/tests/module.build.closure.js
require/resources/tests/module.build.js
require/resources/tests/util.js
require/templatetags/__init__.py
require/templatetags/require.py